{
  "name": "Battleground",
  "className": "DataModel",
  "filePaths": ["battleground.project.json"],
  "children": [
    {
      "name": "ReplicatedStorage",
      "className": "ReplicatedStorage",
      "children": [
        {
          "name": "Design",
          "className": "Folder",
          "children": [
            {
              "name": "NaturePrefabs",
              "className": "ModuleScript",
              "filePaths": ["src/shared/sharedBattleground/Design/NaturePrefabs.luau"]
            },
            {
              "name": "NormalPrefabs",
              "className": "ModuleScript",
              "filePaths": ["src/shared/sharedBattleground/Design/NormalPrefabs.luau"]
            },
            {
              "name": "SpecialPrefabs",
              "className": "ModuleScript",
              "filePaths": ["src/shared/sharedBattleground/Design/SpecialPrefabs.luau"]
            }
          ]
        },
        {
          "name": "Modules",
          "className": "Folder",
          "children": [
            {
              "name": "OccupancyMap",
              "className": "ModuleScript",
              "filePaths": ["src/shared/sharedBattleground/Modules/OccupancyMap.luau"]
            },
            {
              "name": "RiverGenerator",
              "className": "ModuleScript",
              "filePaths": ["src/shared/sharedBattleground/Modules/RiverGenerator.luau"]
            },
            {
              "name": "TerrainConfig",
              "className": "ModuleScript",
              "filePaths": ["src/shared/sharedBattleground/Modules/TerrainConfig.luau"]
            },
            {
              "name": "TerrainUtils",
              "className": "ModuleScript",
              "filePaths": ["src/shared/sharedBattleground/Modules/TerrainUtils.luau"]
            },
            {
              "name": "QuadTree",
              "className": "ModuleScript",
              "filePaths": ["src/shared/sharedBattleground/Modules/QuadTree.luau"]
            }
          ]
        }
      ]
    },
    {
      "name": "ServerScriptService",
      "className": "ServerScriptService",
      "children": [
        {
          "name": "MainTerrainGenerator",
          "className": "Script",
          "filePaths": ["src/server/serverBattleground/MainTerrainGenerator.server.luau"]
        },
        {
          "name": "PlayerSpawner",
          "className": "Script",
          "filePaths": ["src/server/serverBattleground/PlayerSpawner.server.luau"]
        },
        {
          "name": "PrefabSpawner",
          "className": "Script",
          "filePaths": ["src/server/serverBattleground/PrefabSpawner.server.luau"]
        }
      ]
    },
    {
      "name": "StarterPlayer",
      "className": "StarterPlayer",
      "children": [
        {
          "name": "StarterPlayerScripts",
          "className": "StarterPlayerScripts"
        }
      ]
    }
  ]
}